[{"user_id": "246163319", "sentiment": "neg", "rt_count": 180, "user_followers": 1281, "text": "RT @350: We have no alternative but to resist, and resist we will. The Peoples #ClimateMarch on April 29 is going to be huge: https://t.co/\u2026", "created_at": "Tue Apr 25 22:00:24 +0000 2017", "topic": 3, "like_count": 0, "user_friends": 896, "scr_name": "JaneKALuk", "created_at_timestep": 1493157624, "user_avatar": "http://pbs.twimg.com/profile_images/1068576311797530625/16PANiza_normal.jpg", "user_verfied": false, "id": "856991306081554432"}
,{"user_id": "31476142", "sentiment": "neg", "rt_count": 180, "user_followers": 1364, "text": "RT @350: We have no alternative but to resist, and resist we will. The Peoples #ClimateMarch on April 29 is going to be huge: https://t.co/\u2026", "created_at": "Tue Apr 25 22:01:05 +0000 2017", "topic": 3, "like_count": 0, "user_friends": 2579, "scr_name": "JanetteD", "created_at_timestep": 1493157665, "user_avatar": "http://pbs.twimg.com/profile_images/1197577427251281931/eUiZ_TKj_normal.jpg", "user_verfied": false, "id": "856991479213981696"}
,{"user_id": "17847731", "sentiment": "neg", "rt_count": 0, "user_followers": 1417, "text": "Individual action is utterly inadequate to mitigate climate change. That's why we must march https://t.co/dq2HNohYJe #climatemarch", "created_at": "Tue Apr 25 22:01:24 +0000 2017", "topic": 3, "like_count": 0, "user_friends": 1905, "scr_name": "aricclark", "created_at_timestep": 1493157684, "user_avatar": "http://pbs.twimg.com/profile_images/852768093625438213/byo80qfE_normal.jpg", "user_verfied": false, "id": "856991558230343680"}
,{"user_id": "272392038", "sentiment": "neg", "rt_count": 180, "user_followers": 305, "text": "RT @350: We have no alternative but to resist, and resist we will. The Peoples #ClimateMarch on April 29 is going to be huge: https://t.co/\u2026", "created_at": "Tue Apr 25 22:01:49 +0000 2017", "topic": 3, "like_count": 0, "user_friends": 378, "scr_name": "scinterfaith", "created_at_timestep": 1493157709, "user_avatar": "http://pbs.twimg.com/profile_images/1184269129064370176/DLZyJzws_normal.jpg", "user_verfied": false, "id": "856991663138406405"}
,{"user_id": "4721574708", "sentiment": "pos", "rt_count": 14, "user_followers": 4898, "text": "RT @smrtgrls: .@LCVoters\u2019 @T_Sittenfeld: It\u2019s time to raise our voices about #ClimateChange \u2192 https://t.co/XHnojNOPuF @Peoples_Climate #Cli\u2026", "created_at": "Tue Apr 25 22:03:18 +0000 2017", "topic": 3, "like_count": 0, "user_friends": 203, "scr_name": "NRGrenaissance", "created_at_timestep": 1493157798, "user_avatar": "http://pbs.twimg.com/profile_images/876679062151774208/VJ9GZxtq_normal.jpg", "user_verfied": false, "id": "856992037358456832"}
,{"user_id": "263480697", "sentiment": "neg", "rt_count": 180, "user_followers": 1654, "text": "RT @350: We have no alternative but to resist, and resist we will. The Peoples #ClimateMarch on April 29 is going to be huge: https://t.co/\u2026", "created_at": "Tue Apr 25 22:04:59 +0000 2017", "topic": 3, "like_count": 0, "user_friends": 674, "scr_name": "DrBenz3", "created_at_timestep": 1493157899, "user_avatar": "http://pbs.twimg.com/profile_images/1299883002/HeadshotCasual_normal.jpg", "user_verfied": false, "id": "856992461943586816"}
,{"user_id": "4858478950", "sentiment": "neg", "rt_count": 180, "user_followers": 46, "text": "RT @350: We have no alternative but to resist, and resist we will. The Peoples #ClimateMarch on April 29 is going to be huge: https://t.co/\u2026", "created_at": "Tue Apr 25 22:06:01 +0000 2017", "topic": 3, "like_count": 0, "user_friends": 135, "scr_name": "svabbesueco", "created_at_timestep": 1493157961, "user_avatar": "http://pbs.twimg.com/profile_images/692808820071010305/Ylgk_rvy_normal.jpg", "user_verfied": false, "id": "856992722321801218"}
,{"user_id": "2382617130", "sentiment": "pos", "rt_count": 1, "user_followers": 2262, "text": "Circle up with us for some pre- #ClimateMarch strategy! Resist FOMO &amp; fossil fuels at the same time. #YouthRiseUp\ud83d\udcaa\ud83d\udcaa https://t.co/GtoBecOx3E https://t.co/trn5RnuxkH", "created_at": "Tue Apr 25 22:06:20 +0000 2017", "topic": 3, "like_count": 1, "user_friends": 3093, "scr_name": "ourclimateus", "created_at_timestep": 1493157980, "user_avatar": "http://pbs.twimg.com/profile_images/790319257045372928/VsutulRF_normal.jpg", "user_verfied": false, "id": "856992799551438848"}
,{"user_id": "829787503641010176", "sentiment": "pos", "rt_count": 70, "user_followers": 1114, "text": "RT @IMPL0RABLE: #TheResistance #ClimateMarch\n\nGet ready for another big march!\n\nThe #PeoplesClimateMarch on DC: https://t.co/GYqfweNO1O\n\n#R\u2026", "created_at": "Tue Apr 25 22:07:33 +0000 2017", "topic": 3, "like_count": 0, "user_friends": 920, "scr_name": "harmonyis1", "created_at_timestep": 1493158053, "user_avatar": "http://pbs.twimg.com/profile_images/1195083818312462336/ajk-5whn_normal.jpg", "user_verfied": false, "id": "856993106310217728"}
,{"user_id": "185043343", "sentiment": "neg", "rt_count": 180, "user_followers": 96807, "text": "RT @350: We have no alternative but to resist, and resist we will. The Peoples #ClimateMarch on April 29 is going to be huge: https://t.co/\u2026", "created_at": "Tue Apr 25 22:07:34 +0000 2017", "topic": 3, "like_count": 0, "user_friends": 2960, "scr_name": "c40cities", "created_at_timestep": 1493158054, "user_avatar": "http://pbs.twimg.com/profile_images/970791221420371968/ytcvA7cV_normal.jpg", "user_verfied": true, "id": "856993112983576577"}
,{"user_id": "43445412", "sentiment": "neg", "rt_count": 180, "user_followers": 27582, "text": "RT @350: We have no alternative but to resist, and resist we will. The Peoples #ClimateMarch on April 29 is going to be huge: https://t.co/\u2026", "created_at": "Tue Apr 25 22:07:37 +0000 2017", "topic": 3, "like_count": 0, "user_friends": 25703, "scr_name": "DeanLeh", "created_at_timestep": 1493158057, "user_avatar": "http://pbs.twimg.com/profile_images/1164868960132595713/bmUPVSeW_normal.jpg", "user_verfied": false, "id": "856993122944819200"}
,{"user_id": "856123072402870274", "sentiment": "neg", "rt_count": 180, "user_followers": 2422, "text": "RT @350: We have no alternative but to resist, and resist we will. The Peoples #ClimateMarch on April 29 is going to be huge: https://t.co/\u2026", "created_at": "Tue Apr 25 22:08:54 +0000 2017", "topic": 3, "like_count": 0, "user_friends": 2877, "scr_name": "sophie_bussiere", "created_at_timestep": 1493158134, "user_avatar": "http://pbs.twimg.com/profile_images/1187325003290816512/xgPWgfCc_normal.jpg", "user_verfied": false, "id": "856993445176639488"}
,{"user_id": "773110916837740544", "sentiment": "pos", "rt_count": 14, "user_followers": 91, "text": "RT @smrtgrls: .@LCVoters\u2019 @T_Sittenfeld: It\u2019s time to raise our voices about #ClimateChange \u2192 https://t.co/XHnojNOPuF @Peoples_Climate #Cli\u2026", "created_at": "Tue Apr 25 22:10:41 +0000 2017", "topic": 3, "like_count": 0, "user_friends": 100, "scr_name": "N_SFederatedPS", "created_at_timestep": 1493158241, "user_avatar": "http://pbs.twimg.com/profile_images/773111511862697984/_HY7I8kq_normal.jpg", "user_verfied": false, "id": "856993896542461952"}
,{"user_id": "766546824186376192", "sentiment": "neg", "rt_count": 180, "user_followers": 835, "text": "RT @350: We have no alternative but to resist, and resist we will. The Peoples #ClimateMarch on April 29 is going to be huge: https://t.co/\u2026", "created_at": "Tue Apr 25 22:12:54 +0000 2017", "topic": 3, "like_count": 0, "user_friends": 1385, "scr_name": "LizPollitt", "created_at_timestep": 1493158374, "user_avatar": "http://pbs.twimg.com/profile_images/860504407603019776/DTK4mBuT_normal.jpg", "user_verfied": false, "id": "856994453118214145"}
,{"user_id": "885173964", "sentiment": "neg", "rt_count": 180, "user_followers": 191, "text": "RT @350: We have no alternative but to resist, and resist we will. The Peoples #ClimateMarch on April 29 is going to be huge: https://t.co/\u2026", "created_at": "Tue Apr 25 22:14:01 +0000 2017", "topic": 3, "like_count": 0, "user_friends": 218, "scr_name": "jerquee", "created_at_timestep": 1493158441, "user_avatar": "http://pbs.twimg.com/profile_images/2879740670/3705297a3d36fce362afdd93a090a3ea_normal.jpeg", "user_verfied": false, "id": "856994735369539584"}
,{"user_id": "18086309", "sentiment": "neg", "rt_count": 1, "user_followers": 40529, "text": "#ClimateMarch #SaveTheEPA \n\nPeople &amp; Planet over Profits &amp; Corporations \n\n#PruittMustGo\n\nAlso Boycott #TheKochs\n\nhttps://t.co/9YOnJEoeSz", "created_at": "Tue Apr 25 22:29:16 +0000 2017", "topic": 3, "like_count": 3, "user_friends": 33561, "scr_name": "lfkraus", "created_at_timestep": 1493159356, "user_avatar": "http://pbs.twimg.com/profile_images/1003775422398525441/7ffoLWgP_normal.jpg", "user_verfied": false, "id": "856998570125393920"}
,{"user_id": "19984009", "sentiment": "neg", "rt_count": 180, "user_followers": 533, "text": "RT @350: We have no alternative but to resist, and resist we will. The Peoples #ClimateMarch on April 29 is going to be huge: https://t.co/\u2026", "created_at": "Tue Apr 25 22:31:03 +0000 2017", "topic": 3, "like_count": 0, "user_friends": 1217, "scr_name": "EibbedNosredna", "created_at_timestep": 1493159463, "user_avatar": "http://pbs.twimg.com/profile_images/707386246771834880/hEQ_ecNl_normal.jpg", "user_verfied": false, "id": "856999022216785921"}
,{"user_id": "23468714", "sentiment": "neg", "rt_count": 180, "user_followers": 1269, "text": "RT @350: We have no alternative but to resist, and resist we will. The Peoples #ClimateMarch on April 29 is going to be huge: https://t.co/\u2026", "created_at": "Tue Apr 25 22:35:10 +0000 2017", "topic": 3, "like_count": 0, "user_friends": 1954, "scr_name": "bendicoot", "created_at_timestep": 1493159710, "user_avatar": "http://pbs.twimg.com/profile_images/685125623052939264/Y6OeS9CG_normal.jpg", "user_verfied": false, "id": "857000058927153152"}
,{"user_id": "2286145492", "sentiment": "pos", "rt_count": 25, "user_followers": 181, "text": "RT @SierraClub: Alice is coming to the #ClimateMarch for the childhood memories she made in a forest that's now destroyed #WhyIMarch https:\u2026", "created_at": "Tue Apr 25 22:37:14 +0000 2017", "topic": 3, "like_count": 0, "user_friends": 601, "scr_name": "weluvdogs53", "created_at_timestep": 1493159834, "user_avatar": "http://abs.twimg.com/sticky/default_profile_images/default_profile_normal.png", "user_verfied": false, "id": "857000578379075589"}
,{"user_id": "43796613", "sentiment": "pos", "rt_count": 1, "user_followers": 403, "text": "RT @ourclimateus: Circle up with us for some pre- #ClimateMarch strategy! Resist FOMO &amp; fossil fuels at the same time. #YouthRiseUp\ud83d\udcaa\ud83d\udcaa https\u2026", "created_at": "Tue Apr 25 22:37:52 +0000 2017", "topic": 3, "like_count": 0, "user_friends": 527, "scr_name": "CassidyBriann", "created_at_timestep": 1493159872, "user_avatar": "http://pbs.twimg.com/profile_images/1121543348894875648/fC2Zojf0_normal.png", "user_verfied": false, "id": "857000736634265600"}
,{"user_id": "16203788", "sentiment": "neg", "rt_count": 180, "user_followers": 412, "text": "RT @350: We have no alternative but to resist, and resist we will. The Peoples #ClimateMarch on April 29 is going to be huge: https://t.co/\u2026", "created_at": "Tue Apr 25 22:44:00 +0000 2017", "topic": 3, "like_count": 0, "user_friends": 637, "scr_name": "TinTincognito", "created_at_timestep": 1493160240, "user_avatar": "http://pbs.twimg.com/profile_images/1170097464331911168/Vl00kkq__normal.jpg", "user_verfied": false, "id": "857002280935190528"}
,{"user_id": "275220390", "sentiment": "neg", "rt_count": 180, "user_followers": 570, "text": "RT @350: We have no alternative but to resist, and resist we will. The Peoples #ClimateMarch on April 29 is going to be huge: https://t.co/\u2026", "created_at": "Tue Apr 25 22:48:33 +0000 2017", "topic": 3, "like_count": 0, "user_friends": 782, "scr_name": "NaomiPitcairn", "created_at_timestep": 1493160513, "user_avatar": "http://pbs.twimg.com/profile_images/1159955995151327232/F5AIYGe1_normal.jpg", "user_verfied": false, "id": "857003426651062272"}
,{"user_id": "15762770", "sentiment": "neg", "rt_count": 0, "user_followers": 293, "text": "#climatechange Teach In @PennState #climatemarch #PennState https://t.co/yfQdgrHEaE", "created_at": "Tue Apr 25 22:52:49 +0000 2017", "topic": 3, "like_count": 0, "user_friends": 876, "scr_name": "rocofem", "created_at_timestep": 1493160769, "user_avatar": "http://pbs.twimg.com/profile_images/782650809678868480/x-3cHn1z_normal.jpg", "user_verfied": false, "id": "857004499977818112"}
,{"user_id": "532742307", "sentiment": "pos", "rt_count": 7, "user_followers": 4760, "text": "RT @robb_kidd: Let's get ready to march! Here\u2019s what you need to know for the #ClimateMarch this Saturday: Montpelier VT #vtpoli @Peoples_C\u2026", "created_at": "Tue Apr 25 22:58:12 +0000 2017", "topic": 3, "like_count": 0, "user_friends": 5228, "scr_name": "ThayerBerlyn", "created_at_timestep": 1493161092, "user_avatar": "http://pbs.twimg.com/profile_images/1971522891/chesire_normal.jpg", "user_verfied": false, "id": "857005851768487937"}
,{"user_id": "836859560715554817", "sentiment": "neg", "rt_count": 180, "user_followers": 28, "text": "RT @350: We have no alternative but to resist, and resist we will. The Peoples #ClimateMarch on April 29 is going to be huge: https://t.co/\u2026", "created_at": "Tue Apr 25 22:59:06 +0000 2017", "topic": 3, "like_count": 0, "user_friends": 64, "scr_name": "True_Digit", "created_at_timestep": 1493161146, "user_avatar": "http://pbs.twimg.com/profile_images/1194210867702837248/AgbA-ktD_normal.jpg", "user_verfied": false, "id": "857006077887623168"}
,{"user_id": "27249824", "sentiment": "pos", "rt_count": 70, "user_followers": 6304, "text": "RT @IMPL0RABLE: #TheResistance #ClimateMarch\n\nGet ready for another big march!\n\nThe #PeoplesClimateMarch on DC: https://t.co/GYqfweNO1O\n\n#R\u2026", "created_at": "Tue Apr 25 23:02:00 +0000 2017", "topic": 3, "like_count": 0, "user_friends": 6482, "scr_name": "euchreman1022", "created_at_timestep": 1493161320, "user_avatar": "http://pbs.twimg.com/profile_images/1042259198715691008/OPq2sBTm_normal.jpg", "user_verfied": false, "id": "857006811165151232"}
,{"user_id": "62637707", "sentiment": "pos", "rt_count": 0, "user_followers": 668, "text": "We need to stand together to protect our #climate, our #health, and our communities.Join me April 29th https://t.co/hbrDXTsmgN #climatemarch", "created_at": "Tue Apr 25 23:03:00 +0000 2017", "topic": 3, "like_count": 1, "user_friends": 493, "scr_name": "AvalexDynamics", "created_at_timestep": 1493161380, "user_avatar": "http://pbs.twimg.com/profile_images/887699748156825600/iJYnRKvl_normal.jpg", "user_verfied": false, "id": "857007059329572864"}
,{"user_id": "15608555", "sentiment": "pos", "rt_count": 5, "user_followers": 29302, "text": "RT @areik_reik: Fluffing up NoFrackin Wayne the Owl for the Climate March. Stop the auctioning of the Wayne National Forest #climatemarch @\u2026", "created_at": "Tue Apr 25 23:03:01 +0000 2017", "topic": 3, "like_count": 0, "user_friends": 8335, "scr_name": "dominickevans", "created_at_timestep": 1493161381, "user_avatar": "http://pbs.twimg.com/profile_images/510722474221129728/3i0Xz0LK_normal.jpeg", "user_verfied": true, "id": "857007063762968577"}
,{"user_id": "258390253", "sentiment": "pos", "rt_count": 0, "user_followers": 1720, "text": "We need to stand together to protect our climate, our health, and our communities. April 29th https://t.co/LOSgRbrS03 #climatemarch", "created_at": "Tue Apr 25 23:05:03 +0000 2017", "topic": 3, "like_count": 0, "user_friends": 1433, "scr_name": "twokatmew", "created_at_timestep": 1493161503, "user_avatar": "http://pbs.twimg.com/profile_images/1078648979590664192/qtRQ6oM4_normal.jpg", "user_verfied": false, "id": "857007578781536257"}
,{"user_id": "7215512", "sentiment": "pos", "rt_count": 5, "user_followers": 230831, "text": "From @mozuckerman: Here\u2019s why so many young people are joining the #ClimateMarch https://t.co/YL5X9GqJMS https://t.co/lewMkoP17c", "created_at": "Tue Apr 25 23:07:12 +0000 2017", "topic": 3, "like_count": 8, "user_friends": 3056, "scr_name": "grist", "created_at_timestep": 1493161632, "user_avatar": "http://pbs.twimg.com/profile_images/911272673719676928/zU5Y3hOA_normal.jpg", "user_verfied": true, "id": "857008117124669443"}
,{"user_id": "856541502796955649", "sentiment": "pos", "rt_count": 5, "user_followers": 3342, "text": "RT @grist: From @mozuckerman: Here\u2019s why so many young people are joining the #ClimateMarch https://t.co/YL5X9GqJMS https://t.co/lewMkoP17c", "created_at": "Tue Apr 25 23:12:35 +0000 2017", "topic": 3, "like_count": 0, "user_friends": 3519, "scr_name": "movingbackfrom", "created_at_timestep": 1493161955, "user_avatar": "http://pbs.twimg.com/profile_images/856550227318374400/kgyYOyYl_normal.jpg", "user_verfied": false, "id": "857009472136499200"}
,{"user_id": "1179710990", "sentiment": "neg", "rt_count": 1, "user_followers": 8293, "text": "#WhyIMarch: Naomi Klein on \u2018Sacred Duty\u2019 of Participating in #ClimateMarch https://t.co/VDfaQ2n4fp", "created_at": "Tue Apr 25 23:12:36 +0000 2017", "topic": 3, "like_count": 0, "user_friends": 1675, "scr_name": "OccuWorld", "created_at_timestep": 1493161956, "user_avatar": "http://pbs.twimg.com/profile_images/563724232287211520/sEoE-N6j_normal.jpeg", "user_verfied": false, "id": "857009477412937728"}
,{"user_id": "755414445350850560", "sentiment": "pos", "rt_count": 14, "user_followers": 1291, "text": "RT @smrtgrls: .@LCVoters\u2019 @T_Sittenfeld: It\u2019s time to raise our voices about #ClimateChange \u2192 https://t.co/XHnojNOPuF @Peoples_Climate #Cli\u2026", "created_at": "Tue Apr 25 23:14:00 +0000 2017", "topic": 3, "like_count": 0, "user_friends": 1333, "scr_name": "T_Sittenfeld", "created_at_timestep": 1493162040, "user_avatar": "http://pbs.twimg.com/profile_images/1131009540089176069/RoOEu6Hn_normal.jpg", "user_verfied": false, "id": "857009829394739200"}
,{"user_id": "2596654164", "sentiment": "neg", "rt_count": 180, "user_followers": 189, "text": "RT @350: We have no alternative but to resist, and resist we will. The Peoples #ClimateMarch on April 29 is going to be huge: https://t.co/\u2026", "created_at": "Tue Apr 25 23:26:44 +0000 2017", "topic": 3, "like_count": 0, "user_friends": 469, "scr_name": "Lizbit4short", "created_at_timestep": 1493162804, "user_avatar": "http://pbs.twimg.com/profile_images/928728276167733248/SAvAyS9e_normal.jpg", "user_verfied": false, "id": "857013033318699008"}
,{"user_id": "3297899576", "sentiment": "pos", "rt_count": 5, "user_followers": 34, "text": "RT @areik_reik: Fluffing up NoFrackin Wayne the Owl for the Climate March. Stop the auctioning of the Wayne National Forest #climatemarch @\u2026", "created_at": "Tue Apr 25 23:31:46 +0000 2017", "topic": 3, "like_count": 0, "user_friends": 114, "scr_name": "starmina54", "created_at_timestep": 1493163106, "user_avatar": "http://pbs.twimg.com/profile_images/819600866386788352/GL3ASmjJ_normal.jpg", "user_verfied": false, "id": "857014300086587393"}
,{"user_id": "971966480", "sentiment": "neg", "rt_count": 180, "user_followers": 189, "text": "RT @350: We have no alternative but to resist, and resist we will. The Peoples #ClimateMarch on April 29 is going to be huge: https://t.co/\u2026", "created_at": "Tue Apr 25 23:33:21 +0000 2017", "topic": 3, "like_count": 0, "user_friends": 182, "scr_name": "NickD350", "created_at_timestep": 1493163201, "user_avatar": "http://pbs.twimg.com/profile_images/378800000339246929/02993da2dc31bd71ce9edb62b078a865_normal.jpeg", "user_verfied": false, "id": "857014699111657473"}
,{"user_id": "38757535", "sentiment": "neg", "rt_count": 29, "user_followers": 3271, "text": "RT @RachelsNetwork: Save the Planet: Elect Women. #whenwomenlead #climatemarch https://t.co/7O1FxaZEyD https://t.co/KuixRmcPhp", "created_at": "Tue Apr 25 23:34:30 +0000 2017", "topic": 3, "like_count": 0, "user_friends": 1475, "scr_name": "WomenFoodAgNet", "created_at_timestep": 1493163270, "user_avatar": "http://pbs.twimg.com/profile_images/1227281760972570624/jsXNnWLf_normal.jpg", "user_verfied": false, "id": "857014988749275136"}
,{"user_id": "214060210", "sentiment": "neg", "rt_count": 180, "user_followers": 194, "text": "RT @350: We have no alternative but to resist, and resist we will. The Peoples #ClimateMarch on April 29 is going to be huge: https://t.co/\u2026", "created_at": "Tue Apr 25 23:38:05 +0000 2017", "topic": 3, "like_count": 0, "user_friends": 106, "scr_name": "GlobalVisionNet", "created_at_timestep": 1493163485, "user_avatar": "http://pbs.twimg.com/profile_images/1183063332/GVlogoTW_normal.gif", "user_verfied": false, "id": "857015890763816961"}
,{"user_id": "242929999", "sentiment": "neg", "rt_count": 180, "user_followers": 3255, "text": "RT @350: We have no alternative but to resist, and resist we will. The Peoples #ClimateMarch on April 29 is going to be huge: https://t.co/\u2026", "created_at": "Tue Apr 25 23:39:24 +0000 2017", "topic": 3, "like_count": 0, "user_friends": 4979, "scr_name": "CrazyBob48", "created_at_timestep": 1493163564, "user_avatar": "http://pbs.twimg.com/profile_images/1225882074/Rob_Sandy3mini_normal.jpg", "user_verfied": false, "id": "857016222482784256"}
,{"user_id": "634812478", "sentiment": "neg", "rt_count": 2, "user_followers": 3208, "text": "Rick Perry wants to weaken Paris Agreement, which actually needs to be stronger. #climatemarch https://t.co/fUc41GSnb7", "created_at": "Tue Apr 25 23:40:55 +0000 2017", "topic": 3, "like_count": 4, "user_friends": 3997, "scr_name": "cleantechfacts", "created_at_timestep": 1493163655, "user_avatar": "http://pbs.twimg.com/profile_images/1206774567974449157/Ted53bPz_normal.jpg", "user_verfied": false, "id": "857016601979310082"}
,{"user_id": "264114463", "sentiment": "pos", "rt_count": 28, "user_followers": 8823, "text": "RT @AlyssaJohl: In DC for #ClimateMarch? Get started Thurs AM at the Supreme Court! Youth and lawyers of #youthvgov climate lawsuit SPEAK O\u2026", "created_at": "Tue Apr 25 23:41:10 +0000 2017", "topic": 3, "like_count": 0, "user_friends": 3162, "scr_name": "farhanaclimate", "created_at_timestep": 1493163670, "user_avatar": "http://pbs.twimg.com/profile_images/1195245158171840512/nSQ6CYrC_normal.jpg", "user_verfied": false, "id": "857016665007153152"}
,{"user_id": "57164122", "sentiment": "pos", "rt_count": 11, "user_followers": 1666, "text": "RT @UNITEDWEDREAM: What train to catch, what to bring, and... where the portapotties will be. What you need to know for #ClimateMarch https\u2026", "created_at": "Tue Apr 25 23:41:34 +0000 2017", "topic": 3, "like_count": 0, "user_friends": 597, "scr_name": "DnyceDnyce", "created_at_timestep": 1493163694, "user_avatar": "http://pbs.twimg.com/profile_images/956895379479564289/IIR3SBAv_normal.jpg", "user_verfied": false, "id": "857016769013272576"}
,{"user_id": "780991657961517056", "sentiment": "neg", "rt_count": 1, "user_followers": 19637, "text": "@realDonaldTrump There are no crops on a dead planet.\n#ClimateMarch #ClimateChange #ClimateChangeIsReal #SaveTheEPA #ScienceMatters #Resist #TheResistance https://t.co/pnHyBHPaHP", "created_at": "Tue Apr 25 23:42:40 +0000 2017", "topic": 3, "like_count": 4, "user_friends": 18818, "scr_name": "TrumpsBane", "created_at_timestep": 1493163760, "user_avatar": "http://pbs.twimg.com/profile_images/780998146088439808/wnTHryy-_normal.jpg", "user_verfied": false, "id": "857017044914413569"}
,{"user_id": "16317733", "sentiment": "neg", "rt_count": 1, "user_followers": 13842, "text": "RT @TrumpsBane: @realDonaldTrump There are no crops on a dead planet.\n#ClimateMarch #ClimateChange #ClimateChangeIsReal #SaveTheEPA #Scienc\u2026", "created_at": "Tue Apr 25 23:43:12 +0000 2017", "topic": 3, "like_count": 0, "user_friends": 14832, "scr_name": "KibSolFuture", "created_at_timestep": 1493163792, "user_avatar": "http://pbs.twimg.com/profile_images/1054446046515023878/cIRT9CAg_normal.jpg", "user_verfied": false, "id": "857017177479753729"}
,{"user_id": "264451340", "sentiment": "pos", "rt_count": 2, "user_followers": 4685, "text": "RT @cleantechfacts: Rick Perry wants to weaken Paris Agreement, which actually needs to be stronger. #climatemarch https://t.co/fUc41GSnb7", "created_at": "Tue Apr 25 23:43:20 +0000 2017", "topic": 3, "like_count": 0, "user_friends": 5144, "scr_name": "onahunttoday", "created_at_timestep": 1493163800, "user_avatar": "http://abs.twimg.com/sticky/default_profile_images/default_profile_normal.png", "user_verfied": false, "id": "857017210472189952"}
,{"user_id": "807307295470288896", "sentiment": "neg", "rt_count": 1, "user_followers": 1958, "text": "RT @OccuWorld: #WhyIMarch: Naomi Klein on \u2018Sacred Duty\u2019 of Participating in #ClimateMarch https://t.co/VDfaQ2n4fp", "created_at": "Tue Apr 25 23:43:46 +0000 2017", "topic": 3, "like_count": 0, "user_friends": 71, "scr_name": "WhyIMarch", "created_at_timestep": 1493163826, "user_avatar": "http://pbs.twimg.com/profile_images/821733950632574976/qJ6szPyB_normal.jpg", "user_verfied": false, "id": "857017322288148483"}
,{"user_id": "266326338", "sentiment": "pos", "rt_count": 2, "user_followers": 18087, "text": "RT @cleantechfacts: Rick Perry wants to weaken Paris Agreement, which actually needs to be stronger. #climatemarch https://t.co/fUc41GSnb7", "created_at": "Tue Apr 25 23:45:05 +0000 2017", "topic": 3, "like_count": 0, "user_friends": 19034, "scr_name": "rcarr57", "created_at_timestep": 1493163905, "user_avatar": "http://pbs.twimg.com/profile_images/762346657274998784/wCvnRx91_normal.jpg", "user_verfied": false, "id": "857017652149198851"}
,{"user_id": "824126648853393408", "sentiment": "neg", "rt_count": 180, "user_followers": 7, "text": "RT @350: We have no alternative but to resist, and resist we will. The Peoples #ClimateMarch on April 29 is going to be huge: https://t.co/\u2026", "created_at": "Tue Apr 25 23:46:02 +0000 2017", "topic": 3, "like_count": 0, "user_friends": 49, "scr_name": "Revolt_on45", "created_at_timestep": 1493163962, "user_avatar": "http://pbs.twimg.com/profile_images/824143394465259520/DD1YeuMC_normal.jpg", "user_verfied": false, "id": "857017890611933184"}
,{"user_id": "4023256877", "sentiment": "pos", "rt_count": 18, "user_followers": 822, "text": "RT @AdamParkhomenko: There's a historic resistance to Trump\u2019s attacks on people &amp; planet. 4/29 we are standing together! https://t.co/KrxFL\u2026", "created_at": "Tue Apr 25 23:46:34 +0000 2017", "topic": 3, "like_count": 0, "user_friends": 2049, "scr_name": "jcbarnes62", "created_at_timestep": 1493163994, "user_avatar": "http://pbs.twimg.com/profile_images/1165249696232890369/HsRMy4uT_normal.jpg", "user_verfied": false, "id": "857018024242630657"}
,{"user_id": "1066407415", "sentiment": "pos", "rt_count": 5, "user_followers": 233, "text": "RT @cat_abreu: My #marchforscience address! https://t.co/K8XUxNdZJl to @E4Dca for supporting Canadian rallies &amp; to fellow speakers in Ottaw\u2026", "created_at": "Tue Apr 25 23:51:16 +0000 2017", "topic": 3, "like_count": 0, "user_friends": 173, "scr_name": "KinChanPhD", "created_at_timestep": 1493164276, "user_avatar": "http://pbs.twimg.com/profile_images/3074372919/34d34d7bc0db60b674ffc0713a51dc32_normal.jpeg", "user_verfied": false, "id": "857019206914772993"}
]